{"title":"HTML+CSS基础复习完毕","slug":"htmlcss","date":"2017-05-14T07:56:46.000Z","updated":"2019-07-03T13:51:36.848Z","comments":true,"path":"api/articles/htmlcss.json","photos":[],"link":"","excerpt":null,"covers":null,"content":"<p>准备开JS <a href=\"http://be-sunshine.cn/study/\" target=\"_blank\" rel=\"noopener\">http://be-sunshine.cn/study/</a></p>\n","categories":[{"name":"Web","slug":"Web","count":3,"path":"api/categories/Web.json"}],"tags":[{"name":"Web","slug":"Web","count":7,"path":"api/tags/Web.json"}]}