{"title":"索引","slug":"index","date":"2017-10-25T02:46:53.000Z","updated":"2019-07-03T13:51:36.859Z","comments":true,"path":"api/articles/index.json","photos":[],"link":"","excerpt":null,"covers":null,"content":"<p>就相当于加速查找是一个道理,比如c++的map,B树.B+树,平衡搜索树等,为表建立索引也是加快查找速度的一个方法.在数据数量很大的情况下,对用户的体验更友好吧. 在Oracle主要存在以下几种索引:</p>\n<pre><code>B树索引:\ncreate index hir_index on emp(hiredate);\n\nselect index_name,index_type,table_owner,table_name from user_indexes;\n\nselect * from USER_IND_COLUMNS where index_name=&apos;hir_index&apos;;\n\n位图索引(必须建在B树索引之上):\ncreate bitmap index 索引名 on 表名(列名 [ASC|DESC])\n\ncreate bitmap index deptno_index on emp(deptno);\nBITMAP(有几列即几个bit,每个数据集的bit result 与对应位进行|即可以判断是否在表中)\n\n基于函数的索引:\n\n方向键索引(rebuild):\n\n唯一索引:\nCreate unique index\ncreate unique index index_emp_empno on emp();\n\n数据表更新了以后重建索引 rebuild</code></pre>","categories":[{"name":"Oracle","slug":"Oracle","count":2,"path":"api/categories/Oracle.json"}],"tags":[{"name":"Oracle","slug":"Oracle","count":2,"path":"api/tags/Oracle.json"}]}