{"title":"UVa 11181 + UVa 10491","slug":"uva-11181-uva-10491","date":"2017-01-15T15:14:56.000Z","updated":"2019-07-03T13:51:36.845Z","comments":true,"path":"api/articles/uva-11181-uva-10491.json","photos":[],"link":"","excerpt":null,"covers":null,"content":"<p>【类型】 第一题:dfs 全概率 回溯 第二题:全概率 【Tip】 条件概率: P(A|B)=P(AB)|P(B).  P(A|B)指.在事件B的前提下,发生A的概率. P(AB)指两个时间A和B同时发生的概率.P(AB)=P(A)P(B). 全概率: P(A)=P(A|B1)_P(B1)+P(A|B2)_P(B2)+…+P(A|Bn)*P(Bn). 【Code】 11181:</p>\n<blockquote>\n<p><em>#include &lt;stdio.h&gt;</em> <em>#include &lt;string.h&gt;</em> <em>const int N = 30;</em> <em>int n;</em> <em>double p[N], ans[N];</em> <em>double dfs(int c, int k, double pi) {</em> _    if (c &gt; n) return k ? 0 : pi;_ _    double sum = 0;_ _       if (k) {_ _        sum += dfs(c + 1, k - 1, pi * p[c]);//选择_ _        ans[c] += sum;_ _    }_ _    sum += dfs(c + 1, k, pi * (1 - p[c])); //回溯_ _    return sum;_ <em>}</em> <em>int main () {</em> _    int r, cas = 1;_ _    while (scanf(“%d%d”, &amp;n, &amp;r), n + r) {_ _        for (int i = 1; i &lt;= n; i++)_ _            scanf(“%lf”, &amp;p[i]);_ _        memset(ans, 0, sizeof(ans));_ _        printf(“Case %d:\\n”, cas++);_ _        double P = dfs(1, r, 1);_ _        for (int i = 1; i &lt;= n; i++)_ _            printf(“%.6lf\\n”, ans[i] / P);_ _    }_ _    return 0;_ <em>}</em></p>\n</blockquote>\n<p>10491：</p>\n<blockquote>\n<p><em>#include<iostream></iostream></em> <em>#include<algorithm></algorithm></em> <em>#include<cstdio></cstdio></em> <em>using namespace std;</em> <em>int main(){</em> _    int a,b,c;_ _    while(cin&gt;&gt;a&gt;&gt;b&gt;&gt;c){_ _        printf(“%.5lf\\n”,1.0<em>(a*b+b\\</em>(b-1))/((a+b-c-1)*(a+b)));_ _    }_ _    return 0;_ <em>}</em></p>\n</blockquote>\n","categories":[{"name":"UVa","slug":"UVa","count":35,"path":"api/categories/UVa.json"},{"name":"概率论","slug":"UVa/概率论","count":3,"path":"api/categories/UVa/概率论.json"}],"tags":[{"name":"概率论","slug":"概率论","count":4,"path":"api/tags/概率论.json"},{"name":"UVa","slug":"UVa","count":39,"path":"api/tags/UVa.json"}]}