{"name":"CSU","slug":"CSU","count":1,"postlist":[{"title":"CSU 1803","slug":"csu-1803","date":"2017-08-20T07:41:04.000Z","updated":"2019-07-03T13:51:36.851Z","comments":true,"path":"api/articles/csu-1803.json","excerpt":"","keywords":null,"cover":null,"content":"<p>类型: 容斥,唯一分解定理 题目连接: :earth_americas:<a href=\"https://vjudge.net/problem/CSU-1803\" title=\"CSU-1803\" target=\"_blank\" rel=\"noopener\">CSU-1803</a> 题解: 由素分可以得到</p>\n<pre><code>2016=2*2*2*2*2*3*3*7 所以我们可以判断出 a 中有多少2016的因子,然后算出b中与a至少互补的因子个数,利用容斥原理计算出最后的结果.</code></pre><p>github: :moon:<a href=\"https://github.com/834930269/Other_OJ/blob/master/CSU/%E5%AE%B9%E6%96%A5/1803.cpp\" title=\"1803.cpp\" target=\"_blank\" rel=\"noopener\">1803.cpp</a> Code:</p>\n<pre><code>#include&lt;cstdio&gt;\n#include&lt;cstring&gt;\n#include&lt;cstdlib&gt;\n#include&lt;cmath&gt;\nusing namespace std;\ntypedef long long LL;\nLL arr[10][10][10];\nLL a,b;\nint main(){\n    ///2016=2*2*2*2*2*3*3*7\n\n    while(~scanf(&quot;%lld%lld&quot;,&amp;a,&amp;b)){\n        memset(arr,0,sizeof(arr));\n        for(int i=0;i&lt;6;++i)\n            for(int j=0;j&lt;3;++j)\n                for(int t=0;t&lt;2;++t)\n                    arr[i][j][t]=a/(int)(pow(2,i)*pow(3,j)*pow(7,t));\n        LL ans=0;\n        for(int i=0;i&lt;6;++i)\n            for(int j=0;j&lt;3;++j)\n                for(int t=0;t&lt;2;++t)\n                    ans+=(arr[i][j][t]-arr[i+1][j][t]-arr[i][j+1][t]-arr[i][j][t+1]+arr[i+1][j+1][t]+arr[i+1][j][t+1]+arr[i][j+1][t+1]-arr[i+1][j+1][t+1])*(b/(int)(pow(2,5-i)*pow(3,2-j)*pow(7,1-t)));\n        printf(&quot;%lld\\n&quot;,ans);\n    }\n    return 0;\n}</code></pre>","text":"类型: 容斥,唯一分解定理 题目连接: :earth_americas:CSU-1803 题解: 由素分可以得到2016=2*2*2*2*2*3*3*7 所以我们可以判断出 a 中有多少2016的因子,然后算出b中与a至少互补的因子个数,利用容斥原理计算出最后的结果.github","link":"","raw":null,"photos":[],"categories":[{"name":"CSU","slug":"CSU","count":1,"path":"api/categories/CSU.json"},{"name":"唯一分解定理","slug":"CSU/唯一分解定理","count":1,"path":"api/categories/CSU/唯一分解定理.json"},{"name":"容斥原理","slug":"CSU/唯一分解定理/容斥原理","count":1,"path":"api/categories/CSU/唯一分解定理/容斥原理.json"}],"tags":[{"name":"容斥原理","slug":"容斥原理","count":3,"path":"api/tags/容斥原理.json"},{"name":"CSU","slug":"CSU","count":1,"path":"api/tags/CSU.json"},{"name":"唯一分解定理","slug":"唯一分解定理","count":1,"path":"api/tags/唯一分解定理.json"}]}]}